.gitignore
LICENSE
MANIFEST.in
README.rst
VERSION
makefile
setup.py
docs/Makefile
docs/source/conf.py
docs/source/index.rst
docs/source/two_stage.rst
twostage/__init__.py
twostage/quadratic_continued_fraction.py
twostage/two_stage_euclidean.py
twostage.egg-info/PKG-INFO
twostage.egg-info/SOURCES.txt
twostage.egg-info/dependency_links.txt
twostage.egg-info/requires.txt
twostage.egg-info/top_level.txt